notebuild/__init__.py
notebuild/core/__init__.py
notebuild/core/core.py
notebuild/core/version.py
notebuild/git/__init__.py
notebuild/git/repo.py
notebuild/manage/__init__.py
notebuild/manage/core.py
notebuild/manage/port.md
notebuild/manage/supervisord.conf
notebuild/shell/__init__.py
notebuild/shell/core.py
notebuild/temp/__init__.py
notebuild/temp/core.json
notebuild/temp/core.py
notebuild/tool/__init__.py
notebuild/tool/build.py
notebuild/tool/fastapi.py
notebuild-1.3.9.dist-info/LICENSE
notebuild-1.3.9.dist-info/METADATA
notebuild-1.3.9.dist-info/WHEEL
notebuild-1.3.9.dist-info/entry_points.txt
notebuild-1.3.9.dist-info/top_level.txt
notebuild-1.3.9.dist-info/RECORD
