Metadata-Version: 2.1
Name: notebuild
Version: 1.3.9
Summary: notebuild
Home-page: https://github.com/1007530194
Author: niuliangtao
Author-email: 1007530194@qq.com
License: UNKNOWN
Platform: UNKNOWN
License-File: LICENSE
Requires-Dist: GitPython
